baynet/__init__.py
baynet/metrics.py
baynet/parameters.py
baynet/structure.py
baynet/structure_generation.py
baynet/utils/DAG_pb2.py
baynet/utils/__init__.py
baynet/utils/dag_io.py
baynet/utils/visualisation.py
baynet/utils/bif_library/alarm.bif
baynet/utils/bif_library/andes.bif
baynet/utils/bif_library/asia.bif
baynet/utils/bif_library/barley.bif
baynet/utils/bif_library/cancer.bif
baynet/utils/bif_library/child.bif
baynet/utils/bif_library/diabetes.bif
baynet/utils/bif_library/earthquake.bif
baynet/utils/bif_library/hailfinder.bif
baynet/utils/bif_library/hepar2.bif
baynet/utils/bif_library/insurance.bif
baynet/utils/bif_library/link.bif
baynet/utils/bif_library/mildew.bif
baynet/utils/bif_library/munin.bif
baynet/utils/bif_library/pathfinder.bif
baynet/utils/bif_library/pigs.bif
baynet/utils/bif_library/sachs.bif
baynet/utils/bif_library/survey.bif
baynet/utils/bif_library/water.bif
baynet/utils/bif_library/win95pts.bif
BayNet-0.3.0.dist-info/METADATA
BayNet-0.3.0.dist-info/WHEEL
BayNet-0.3.0.dist-info/top_level.txt
BayNet-0.3.0.dist-info/RECORD
